{
  "scenarioFolder": "Pruefungsvorbereitung-2-FIAE-Scenarien",
  "quizFolder": "Pruefungsvorbereitung-2-FIAE-Quiz",
  "items": [
    {
      "file": "quiz_ap2_fiae_gesamtpool/quiz01_V01_ap2_fiae_gesamtpool.json",
      "label": "AP2 FIAE Gesamtpool",
      "ticketId": "pv2_fiae_gesamtpool.json",
      "versionId": "V01",
      "questionCount": 1560,
      "topics": [
        "Algorithmen und Pseudocode",
        "UML und OOP",
        "Datenmodellierung und Normalisierung",
        "SQL und Datenbankpraxis",
        "Testen und Qualitätssicherung",
        "Sicherheit und Datenschutz",
        "Web, APIs und Architektur",
        "Anforderungen und UX",
        "Erweiterte Praxis"
      ],
      "interactionTypes": [
        "best",
        "binary",
        "multi",
        "single"
      ],
      "questionKinds": [
        "aussage_bewerten",
        "begriff_zu_definition",
        "beispiel_erkennen",
        "beste_option_im_mini_szenario",
        "definition_zu_begriff",
        "fehler_finden",
        "gegenbeispiel_erkennen",
        "mehrere_richtige_antworten_waehlen",
        "passende_massnahme_auswaehlen",
        "ursache_folge_erkennen",
        "vergleich_treffen",
        "was_fehlt",
        "ziel_mittel_zuordnung"
      ],
      "dominantBadge": "Lernkarte"
    }
  ]
}
